psh2bat/__init__.py
psh2bat/app.py
psh2bat/cli.py
psh2bat/config.py
psh2bat/convert.py
psh2bat/logger.py
psh2bat/main.py
psh2bat/utils.py
psh2bat/version.py
psh2bat-0.0.4.dist-info/licenses/LICENSE
psh2bat-0.0.4.dist-info/METADATA
psh2bat-0.0.4.dist-info/WHEEL
psh2bat-0.0.4.dist-info/entry_points.txt
psh2bat-0.0.4.dist-info/top_level.txt
psh2bat-0.0.4.dist-info/RECORD
